README.md
pyproject.toml
setup.py
flydrone/__init__.py
flydrone/drone.py
flydrone.egg-info/PKG-INFO
flydrone.egg-info/SOURCES.txt
flydrone.egg-info/dependency_links.txt
flydrone.egg-info/requires.txt
flydrone.egg-info/top_level.txt