Metadata-Version: 2.1
Name: flydrone
Version: 0.0.1
Summary: A simple basic drone python api that is built on top of pymavlink
Home-page: https://github.com/AnmarHani/PyDrone
Author: Anmar Hani
Author-email: AnmarHaniV1@gmail.com
License: MIT
Keywords: python,drone,embedded,automation
Classifier: Development Status :: 4 - Beta
Classifier: Intended Audience :: Developers
Classifier: License :: OSI Approved :: MIT License
Classifier: Programming Language :: Python :: 3.8
Classifier: Operating System :: OS Independent
